setup.py
django_analyze/__init__.py
django_analyze/admin.py
django_analyze/constants.py
django_analyze/models.py
django_analyze/timeout.py
django_analyze/utils.py
django_analyze/yajl_simple.py
django_analyze.egg-info/PKG-INFO
django_analyze.egg-info/SOURCES.txt
django_analyze.egg-info/dependency_links.txt
django_analyze.egg-info/requires.txt
django_analyze.egg-info/top_level.txt
django_analyze/management/__init__.py
django_analyze/management/commands/__init__.py
django_analyze/management/commands/apply_genome.py
django_analyze/management/commands/clean_genotypes.py
django_analyze/management/commands/clone_genotype.py
django_analyze/management/commands/compile_genome_error_report.py
django_analyze/management/commands/delete_genes.py
django_analyze/management/commands/dump_genome.py
django_analyze/management/commands/evolve_population.py
django_analyze/management/commands/load_genome.py
django_analyze/management/commands/organize_species.py
django_analyze/management/commands/prepare_genomes.py
django_analyze/management/commands/test_multiprogress.py
django_analyze/management/commands/update_gene_statistics.py
django_analyze/migrations/0001_initial.py
django_analyze/migrations/0002_auto__chg_field_gene_default.py
django_analyze/migrations/0003_auto__add_field_genotype_gene_count.py
django_analyze/migrations/0004_auto__add_unique_genotype_genome_fingerprint.py
django_analyze/migrations/0005_auto__add_field_genome_max_fitness__add_field_genome_min_fitness.py
django_analyze/migrations/0006_auto__add_field_genome_evaluator.py
django_analyze/migrations/0007_auto__add_field_genotype_mean_training_seconds.py
django_analyze/migrations/0008_auto__add_field_genome_admin_extender.py
django_analyze/migrations/0009_auto__add_field_genome_evaluation_timeout.py
django_analyze/migrations/0010_auto__del_field_genome_admin_extender.py
django_analyze/migrations/0011_auto__add_field_genotype_fresh.py
django_analyze/migrations/0012_auto__del_field_genotype_mean_training_seconds__add_field_genotype_mea.py
django_analyze/migrations/0013_auto__chg_field_genotype_fresh.py
django_analyze/migrations/0014_auto__add_field_gene_dependee_gene__add_field_gene_dependee_value.py
