Metadata-Version: 1.1
Name: django-analyze
Version: 0.4.20
Summary: A general purpose framework for training and testing classification algorithms.
Home-page: https://github.com/chrisspen/django-analyze
Author: Chris Spencer
Author-email: chrisspen@gmail.com
License: LGPL
Platform: UNKNOWN
Classifier: Development Status :: 3 - Alpha
Classifier: Environment :: Web Environment
Classifier: Intended Audience :: Developers
Classifier: License :: OSI Approved :: GNU Lesser General Public License v3 (LGPLv3)
Classifier: Operating System :: OS Independent
Classifier: Programming Language :: Python
Classifier: Framework :: Django
Classifier: Topic :: Scientific/Engineering :: Artificial Intelligence
